llm_templates_latitude.py
llm_templates_latitude-0.3.0.dist-info/METADATA
llm_templates_latitude-0.3.0.dist-info/WHEEL
llm_templates_latitude-0.3.0.dist-info/entry_points.txt
llm_templates_latitude-0.3.0.dist-info/RECORD
