Metadata-Version: 2.4
Name: llm-templates-latitude
Version: 0.3.0
Summary: LLM template loader for Latitude - Load prompts from Latitude as LLM templates
Project-URL: Homepage, https://github.com/pcaro/llm-templates-latitude
Project-URL: Issues, https://github.com/pcaro/llm-templates-latitude/issues
Author-email: Pablo Caro Revuelta <correo@pablocaro.es>
License: Apache-2.0
Classifier: Development Status :: 3 - Alpha
Classifier: Intended Audience :: Developers
Classifier: License :: OSI Approved :: Apache Software License
Classifier: Programming Language :: Python :: 3
Classifier: Programming Language :: Python :: 3.9
Classifier: Programming Language :: Python :: 3.10
Classifier: Programming Language :: Python :: 3.11
Classifier: Programming Language :: Python :: 3.12
Requires-Python: >=3.9
Requires-Dist: httpx>=0.24.0
Requires-Dist: latitude-sdk>=1.0.0
Requires-Dist: llm>=0.13
Requires-Dist: pydantic>=2.0
Requires-Dist: python-dotenv>=1.0.0
